pheflux/#create_contraints.py#
pheflux/#pheflux.py#
pheflux/__init__.py
pheflux/boolean_vector_rule.py
pheflux/create_constraints.py
pheflux/forward_reverse.py
pheflux/get_eg.py
pheflux/get_g.py
pheflux/get_primal.py
pheflux/item.py
pheflux/load_fpkm.py
pheflux/main.py
pheflux/measure_time.py
pheflux/opt_phe_flux.py
pheflux/parser.out
pheflux/parsetab.py
pheflux/ppre_heflux.py
pheflux/primal_values.py
pheflux/read_settings.py
pheflux/record.py
pheflux/reload_fpkmh_sapiens.py
pheflux/save_rules.py
pheflux/set_variables.py
pheflux/sum_v.py
pheflux/update_model.py
pheflux/utils.py
pheflux-0.2.0.dist-info/METADATA
pheflux-0.2.0.dist-info/WHEEL
pheflux-0.2.0.dist-info/RECORD
